LICENSE
MANIFEST.in
Readme.rst
setup.py
warc3_wet_clueweb09/__init__.py
warc3_wet_clueweb09/arc.py
warc3_wet_clueweb09/utils.py
warc3_wet_clueweb09/warc.py
warc3_wet_clueweb09.egg-info/PKG-INFO
warc3_wet_clueweb09.egg-info/SOURCES.txt
warc3_wet_clueweb09.egg-info/dependency_links.txt
warc3_wet_clueweb09.egg-info/top_level.txt