Metadata-Version: 1.1
Name: warc3-wet-clueweb09
Version: 0.2.4
Summary: Python library to work with ARC and WARC files, with fixes for ClueWeb09
Home-page: https://github.com/seanmacavaney/warc3-clueweb
Author: Anand Chitipothu, Noufal Ibrahim, Ryan Chartier, Jan Pieter Bruins Slot, Almer S. Tigelaar, Willian Zhang
Author-email: info@archive.org
License: GPLv2
Platform: any
Classifier: Development Status :: 4 - Beta
Classifier: Environment :: Web Environment
Classifier: Intended Audience :: Developers
Classifier: License :: OSI Approved :: GNU General Public License v2 (GPLv2)
Classifier: Operating System :: OS Independent
Classifier: Programming Language :: Python
